calc_norm/__init__.py
calc_norm/basic_calc.py
calc_norm-0.1.0.dist-info/METADATA
calc_norm-0.1.0.dist-info/WHEEL
calc_norm-0.1.0.dist-info/entry_points.txt
calc_norm-0.1.0.dist-info/RECORD
