Metadata-Version: 2.4
Name: calc-norm
Version: 0.1.0
Summary: Add your description here
Author-email: urstrulyrohans <urstrulyrohansd@gmail.com>
Requires-Python: >=3.12
Requires-Dist: setuptools>=80.8.0
